jupyter_manager/__init__.py
jupyter_manager/__main__.py
jupyter_manager/_version.py
jupyter_manager/application.py
jupyter_manager/generate_config.py
jupyter_manager/handlers.py
jupyter_manager/load_config.py
jupyter_manager/server_config.py
jupyter_manager/shim_config.py
jupyter_manager/static/README.md
jupyter_manager/static/main.jupyterManager.js
jupyter_manager/templates/index.html
jupyter_manager/tests/__init__.py
jupyter_manager/tests/test_generate_config.py
jupyter_manager/tests/test_genson.py
jupyter_manager/tests/test_handlers.py
jupyter_manager/tests/test_load_config.py
jupyter_manager/tests/test_server_extensions.py
jupyter_manager/tests/test_shim_config.py
jupyter_manager/tests/config_1/jupyter_notebook_config.py
jupyter_manager/tests/config_1/jupyter_server_config.py
jupyter_manager/tests/config_2/jupyter_my_ext_config.py
jupyter_manager/tests/config_2/jupyter_notebook_config.py
jupyter_manager/tests/config_2/jupyter_server_config.py
jupyter_manager-0.0.4.data/data/etc/jupyter/jupyter_notebook_config.d/jupyter_manager.json
jupyter_manager-0.0.4.data/data/etc/jupyter/jupyter_server_config.d/jupyter_manager.json
jupyter_manager-0.0.4.data/data/share/jupyter/labextensions/@datalayer/jupyter-manager/build_log.json
jupyter_manager-0.0.4.data/data/share/jupyter/labextensions/@datalayer/jupyter-manager/install.json
jupyter_manager-0.0.4.data/data/share/jupyter/labextensions/@datalayer/jupyter-manager/package.json
jupyter_manager-0.0.4.data/data/share/jupyter/labextensions/@datalayer/jupyter-manager/schemas/@datalayer/jupyter-manager/package.json.orig
jupyter_manager-0.0.4.data/data/share/jupyter/labextensions/@datalayer/jupyter-manager/schemas/@datalayer/jupyter-manager/plugin.json
jupyter_manager-0.0.4.data/data/share/jupyter/labextensions/@datalayer/jupyter-manager/static/lib_index_js.bc40d18dc7d7195bb06f.js
jupyter_manager-0.0.4.data/data/share/jupyter/labextensions/@datalayer/jupyter-manager/static/lib_index_js.bc40d18dc7d7195bb06f.js.map
jupyter_manager-0.0.4.dist-info/METADATA
jupyter_manager-0.0.4.dist-info/WHEEL
jupyter_manager-0.0.4.dist-info/entry_points.txt
jupyter_manager-0.0.4.dist-info/licenses/LICENSE
jupyter_manager-0.0.4.dist-info/RECORD
