Metadata-Version: 2.1
Name: jupyter_manager
Version: 0.0.4
Summary: 🪐 ⚙️ User interface to manage your Jupyter platform.
Project-URL: Homepage, https://github.com/datalayer/jupyter-manager
Project-URL: Bug Tracker, https://github.com/datalayer/jupyter-manager/issues
Project-URL: Repository, https://github.com/datalayer/jupyter-manager.git
Author-email: Datalayer <info@datalayer.io>
License: Contains source code taken from https://github.com/jupyterhub/jupyterhub under BSD 3-Clause License.
License-File: LICENSE
Classifier: Framework :: Jupyter
Classifier: Framework :: Jupyter :: JupyterLab
Classifier: Framework :: Jupyter :: JupyterLab :: 3
Classifier: Framework :: Jupyter :: JupyterLab :: Extensions
Classifier: Framework :: Jupyter :: JupyterLab :: Extensions :: Prebuilt
Classifier: License :: OSI Approved :: BSD License
Classifier: Programming Language :: Python
Classifier: Programming Language :: Python :: 3
Classifier: Programming Language :: Python :: 3.9
Classifier: Programming Language :: Python :: 3.10
Classifier: Programming Language :: Python :: 3.11
Requires-Python: >=3.9
Requires-Dist: genson
Requires-Dist: jupyter-server<3,>=2.0
Requires-Dist: jupyterlab==4.0.0
Provides-Extra: test
Requires-Dist: coverage; extra == 'test'
Requires-Dist: pytest; extra == 'test'
Requires-Dist: pytest-asyncio; extra == 'test'
Requires-Dist: pytest-cov; extra == 'test'
Requires-Dist: pytest-jupyter; extra == 'test'
Requires-Dist: pytest-tornasync; extra == 'test'
